fprime/__init__.py
fprime/constants.py
fprime/common/__init__.py
fprime/common/error.py
fprime/common/utils.py
fprime/common/models/__init__.py
fprime/common/models/serialize/__init__.py
fprime/common/models/serialize/array_type.py
fprime/common/models/serialize/bool_type.py
fprime/common/models/serialize/enum_type.py
fprime/common/models/serialize/numerical_types.py
fprime/common/models/serialize/serializable_type.py
fprime/common/models/serialize/string_type.py
fprime/common/models/serialize/time_type.py
fprime/common/models/serialize/type_base.py
fprime/common/models/serialize/type_exceptions.py
fprime/cookiecutter_templates/cookiecutter-fprime-component/cookiecutter.json
fprime/cookiecutter_templates/cookiecutter-fprime-component/hooks/pre_gen_project.py
fprime/cookiecutter_templates/cookiecutter-fprime-component/{{cookiecutter.component_name}}/CMakeLists.txt
fprime/cookiecutter_templates/cookiecutter-fprime-component/{{cookiecutter.component_name}}/{{cookiecutter.component_name}}.cpp
fprime/cookiecutter_templates/cookiecutter-fprime-component/{{cookiecutter.component_name}}/{{cookiecutter.component_name}}.fpp
fprime/cookiecutter_templates/cookiecutter-fprime-component/{{cookiecutter.component_name}}/{{cookiecutter.component_name}}.hpp
fprime/cookiecutter_templates/cookiecutter-fprime-component/{{cookiecutter.component_name}}/docs/sdd.md
fprime/cookiecutter_templates/cookiecutter-fprime-deployment/cookiecutter.json
fprime/cookiecutter_templates/cookiecutter-fprime-deployment/hooks/pre_gen_project.py
fprime/cookiecutter_templates/cookiecutter-fprime-deployment/{{cookiecutter.deployment_name}}/CMakeLists.txt
fprime/cookiecutter_templates/cookiecutter-fprime-deployment/{{cookiecutter.deployment_name}}/Main.cpp
fprime/cookiecutter_templates/cookiecutter-fprime-deployment/{{cookiecutter.deployment_name}}/README.md
fprime/cookiecutter_templates/cookiecutter-fprime-deployment/{{cookiecutter.deployment_name}}/Top/CMakeLists.txt
fprime_tools-4.0.1.dist-info/licenses/LICENSE.txt
fprime_tools-4.0.1.dist-info/licenses/NOTICE.txt
fprime_tools-4.0.1.dist-info/METADATA
fprime_tools-4.0.1.dist-info/WHEEL
fprime_tools-4.0.1.dist-info/entry_points.txt
fprime_tools-4.0.1.dist-info/top_level.txt
fprime_tools-4.0.1.dist-info/RECORD
