Metadata-Version: 2.4
Name: fprime-tools
Version: 4.0.1
Summary: F Prime Flight Software tooling, helpers and core data types
Author-email: Michael Starch <Michael.D.Starch@jpl.nasa.gov>, Thomas Boyer-Chammard <Thomas.Boyer.Chammard@jpl.nasa.gov>
License: 
Project-URL: Homepage, https://fprime.jpl.nasa.gov
Project-URL: Documentation, https://nasa.github.io/fprime/
Project-URL: Repository, https://github.com/fprime-community/fprime-tools
Keywords: fprime,embedded,nasa,flight,software
Classifier: Development Status :: 5 - Production/Stable
Classifier: Intended Audience :: Developers
Classifier: Operating System :: Unix
Classifier: Operating System :: POSIX
Classifier: Programming Language :: Python
Classifier: Programming Language :: Python :: 3
Classifier: Programming Language :: Python :: 3.9
Classifier: Programming Language :: Python :: 3.10
Classifier: Programming Language :: Python :: 3.11
Classifier: Programming Language :: Python :: 3.12
Classifier: Programming Language :: Python :: Implementation :: CPython
Classifier: Programming Language :: Python :: Implementation :: PyPy
Classifier: License :: OSI Approved :: Apache Software License
Requires-Python: >=3.9
License-File: LICENSE.txt
License-File: NOTICE.txt
Requires-Dist: Markdown>=3.3.4
Requires-Dist: pexpect>=4.8.0
Requires-Dist: pytest>=6.2.4
Requires-Dist: cookiecutter>=2.2.3
Requires-Dist: gcovr>=6.0
Requires-Dist: urllib3>=2.5.0
Requires-Dist: requests>=2.31.0
Provides-Extra: test
Requires-Dist: pytest; extra == "test"
Provides-Extra: dev
Requires-Dist: black; extra == "dev"
Requires-Dist: pylama; extra == "dev"
Requires-Dist: pylint; extra == "dev"
Requires-Dist: pre-commit; extra == "dev"
Requires-Dist: sphinx; extra == "dev"
Requires-Dist: sphinxcontrib.mermaid; extra == "dev"
Requires-Dist: sphinx-rtd-theme; extra == "dev"
Requires-Dist: sphinx-autoapi; extra == "dev"
Requires-Dist: sphinx-autoapi; extra == "dev"
Requires-Dist: recommonmark; extra == "dev"
Dynamic: license-file
